phoneTUIapp/__init__.py
phoneTUIapp/phoneTUI.py
phoneTUIapp-1.0.0.dist-info/METADATA
phoneTUIapp-1.0.0.dist-info/WHEEL
phoneTUIapp-1.0.0.dist-info/entry_points.txt
phoneTUIapp-1.0.0.dist-info/top_level.txt
phoneTUIapp-1.0.0.dist-info/RECORD
