Metadata-Version: 2.1
Name: phoneTUIapp
Version: 1.0.0
Summary: A TUI application for viewing calls and SMS
Home-page: https://github.com/x07sh/phone/phoneTUIapp
Author: Anurag Kanase
Author-email: anuwrag@gmail.com
Classifier: Programming Language :: Python :: 3
Classifier: License :: OSI Approved :: MIT License
Classifier: Operating System :: OS Independent
Requires-Python: >=3.6
Requires-Dist: npyscreen
